at_common_util/__init__.py
at_common_util/db/__init__.py
at_common_util/db/query.py
at_common_util/db/storage.py
at_common_util/workflow/__init__.py
at_common_util/workflow/core/__init__.py
at_common_util/workflow/core/constants.py
at_common_util/workflow/core/context.py
at_common_util/workflow/core/exceptions.py
at_common_util/workflow/core/task/__init__.py
at_common_util/workflow/core/task/base.py
at_common_util/workflow/core/task/builder.py
at_common_util/workflow/core/task/definition.py
at_common_util/workflow/core/task/processing_task.py
at_common_util/workflow/core/task/validation.py
at_common_util/workflow/core/workflow/__init__.py
at_common_util/workflow/core/workflow/base.py
at_common_util/workflow/core/workflow/builder.py
at_common_util/workflow/core/workflow/node.py
at_common_util/workflow/core/workflow/execution/events.py
at_common_util/workflow/core/workflow/execution/executor.py
at_common_util/workflow/core/workflow/execution/progress.py
at_common_util/workflow/core/workflow/graph/__init__.py
at_common_util/workflow/core/workflow/graph/dependency.py
at_common_util/workflow/core/workflow/graph/dependency_adapter.py
at_common_util/workflow/core/workflow/graph/dependency_graph.py
at_common_util/workflow/utils/__init__.py
at_common_util/workflow/utils/logging.py
at_common_util/workflow/utils/mappings.py
at_common_util-0.1.3.dist-info/METADATA
at_common_util-0.1.3.dist-info/WHEEL
at_common_util-0.1.3.dist-info/top_level.txt
at_common_util-0.1.3.dist-info/RECORD
