Metadata-Version: 2.4
Name: at-common-util
Version: 0.1.3
Summary: A robust Python package for building and executing asynchronous workflow tasks in a directed acyclic graph (DAG) pattern. This package provides a type-safe, thread-safe framework for defining, organizing, and running dependent tasks with comprehensive validation and error handling.
Author-email: Rui Chen <apextrader.ai@gmail.com>
Project-URL: Homepage, https://github.com/apex-trader/at-common-workflow
Project-URL: Bug Tracker, https://github.com/apex-trader/at-common-workflow/issues
Classifier: Programming Language :: Python :: 3
Classifier: License :: OSI Approved :: MIT License
Classifier: Operating System :: OS Independent
Requires-Python: >=3.11
Requires-Dist: pydantic>=2.10.6
Requires-Dist: typing_extensions>=4.12.2
Requires-Dist: sqlalchemy>=2.0.0
Requires-Dist: sqlalchemy-utils>=0.40.0
Requires-Dist: asyncpg>=0.27.0
Provides-Extra: dev
Requires-Dist: pytest>=8.3.4; extra == "dev"
Requires-Dist: pytest-asyncio>=0.25.3; extra == "dev"
Requires-Dist: black>=22.1.0; extra == "dev"
Requires-Dist: isort>=5.10.1; extra == "dev"
Requires-Dist: mypy>=0.931; extra == "dev"
